setup.py
PearPyPac/CGI.py
PearPyPac/DB.py
PearPyPac/Util.py
PearPyPac/__init__.py
PearPyPac.egg-info/PKG-INFO
PearPyPac.egg-info/SOURCES.txt
PearPyPac.egg-info/dependency_links.txt
PearPyPac.egg-info/requires.txt
PearPyPac.egg-info/top_level.txt