Metadata-Version: 1.0
Name: PearPyPac
Version: 0.1.9
Summary: pear library
Home-page: https://github.com/HirokiUmatani/PearPackage
Author: Hiroki Umatani
Author-email: h_umatani@pear.chat
License: MIT
Keywords: PearPyPac,pear
Platform: UNKNOWN
